[{"score":0,"password":"c09c55d3132959f34bf689e7cf61ea607b3440d9ffb83bc7e35f006fcfebb657","answerToSecurityQuestion":"joe","nickName":"ali","securityQuestionNumber":"Was my first pet\u2019s name?","isLoggedIn":true,"avatar":"file:\/Users\/mohammadhosseinboroumandnia\/Desktop\/project-group-38\/target\/classes\/images\/avatars\/1.jpg","userName":"u1","slogan":"","email":"e1@g.c"},{"score":0,"password":"c09c55d3132959f34bf689e7cf61ea607b3440d9ffb83bc7e35f006fcfebb657","answerToSecurityQuestion":"Ali","nickName":"ali","securityQuestionNumber":"What is my father\u2019s name?","isLoggedIn":false,"avatar":"file:\/Users\/mohammadhosseinboroumandnia\/Desktop\/project-group-38\/target\/classes\/images\/avatars\/1.jpg","userName":"u2","slogan":"","email":"e2@g.c"}]
